README.rst
fecru.py
setup.py
FecruEvry.egg-info/PKG-INFO
FecruEvry.egg-info/SOURCES.txt
FecruEvry.egg-info/dependency_links.txt
FecruEvry.egg-info/requires.txt
FecruEvry.egg-info/top_level.txt