Metadata-Version: 1.0
Name: FecruEvry
Version: 0.7a1.dev0
Summary: A python client to the Atlassian FECRU REST API
Home-page: https://github.com/dobbscr/python-fecru
Author: Christopher Richard Dobbs
Author-email: christopher.dobbs@evry.com
License: BSD
Platform: UNKNOWN
Classifier: Development Status :: 4 - Beta
Classifier: Intended Audience :: Developers
Classifier: License :: OSI Approved :: BSD License
Classifier: Programming Language :: Python
Classifier: Programming Language :: Python :: 2.7
Classifier: Programming Language :: Python :: 3.3
Classifier: Topic :: Software Development :: Libraries :: Python Modules
Classifier: Topic :: System :: Systems Administration :: Authentication/Directory
